punctilious/__init__.py
punctilious/caller_info.py
punctilious/core.py
punctilious/graph.py
punctilious/locale_en_us.py
punctilious/plaintext.py
punctilious/random_data.py
punctilious/repm.py
punctilious/reserved_words.py
punctilious/unicode_utilities.py
sample/__init__.py
sample/sample_absorption.py
sample/sample_axiom_interpretation.py
sample/sample_biconditional_elimination_1.py
sample/sample_biconditional_elimination_2.py
sample/sample_biconditional_introduction.py
sample/sample_conjunction_elimination_1.py
sample/sample_conjunction_elimination_2.py
sample/sample_conjunction_introduction.py
sample/sample_constant.py
sample/sample_constructive_dilemma.py
sample/sample_definition_interpretation.py
sample/sample_destructive_dilemma.py
sample/sample_disjunction_introduction_1.py
sample/sample_disjunction_introduction_2.py
sample/sample_disjunctive_resolution.py
sample/sample_disjunctive_syllogism_1.py
sample/sample_disjunctive_syllogism_2.py
sample/sample_double_negation_elimination.py
sample/sample_double_negation_introduction.py
sample/sample_equal_terms_substitution.py
sample/sample_equality_commutativity.py
sample/sample_export_all_articles.py
sample/sample_hypothesis.py
sample/sample_hypothetical_syllogism.py
sample/sample_inconsistency_introduction_1.py
sample/sample_inconsistency_introduction_2.py
sample/sample_inconsistency_introduction_3.py
sample/sample_iterate_formula_data_model_components.py
sample/sample_modus_ponens.py
sample/sample_modus_tollens.py
sample/sample_pet_theory_1.py
sample/sample_proof_by_contradiction_1.py
sample/sample_proof_by_contradiction_2.py
sample/sample_proof_by_refutation_1.py
sample/sample_proof_by_refutation_2.py
sample/sample_sandbox.py
sample/sample_universe_of_discourse.py
sample/sample_variable.py
sample/sample_variable_substitution.py
theory/__init__.py
theory/punctilious_2023_metatheory_OBSOLETE.py
theory/theory_mgz_2021_classical_logic_j0.py
theory/theory_mgz_2021_intuitionistic_logic_j0.py
punctilious-1.0.10.dist-info/LICENSE
punctilious-1.0.10.dist-info/METADATA
punctilious-1.0.10.dist-info/WHEEL
punctilious-1.0.10.dist-info/top_level.txt
punctilious-1.0.10.dist-info/RECORD
