Metadata-Version: 2.1
Name: punctilious
Version: 1.0.10
Summary: A human-friendly and developer-friendly math proof assistant
Author-email: David Doret <david.doret@icloud.com>
Project-URL: Homepage, https://github.com/daviddoret/punctilious
Project-URL: Bug Tracker, https://github.com/daviddoret/punctilious/issues
Project-URL: Documentation, https://punctilious.readthedocs.io/en/latest/
Project-URL: Repository, https://github.com/daviddoret/punctilious
Keywords: math,mathematics,proof,proof assistant,math proof assistant,formal system
Classifier: Development Status :: 4 - Beta
Classifier: Intended Audience :: Developers
Classifier: Intended Audience :: Education
Classifier: Intended Audience :: Science/Research
Classifier: Programming Language :: Python
Classifier: Programming Language :: Python :: 3
Classifier: License :: OSI Approved :: MIT License
Classifier: Natural Language :: English
Classifier: Operating System :: OS Independent
Classifier: Topic :: Education
Classifier: Topic :: Scientific/Engineering
Classifier: Topic :: Scientific/Engineering :: Mathematics
Requires-Python: >=3.11
License-File: LICENSE
